ipnd/__init__.py
ipnd/ipnd.py
ipnd/record.py
ipnd/utils.py
au_ipnd-0.0.2.dist-info/METADATA
au_ipnd-0.0.2.dist-info/WHEEL
au_ipnd-0.0.2.dist-info/top_level.txt
au_ipnd-0.0.2.dist-info/RECORD
