Metadata-Version: 2.1
Name: au-ipnd
Version: 0.0.2
Summary: Australian IPND Client
Home-page: https://github.com/Divoli/ipnd
Author: Devoli
Author-email: dev@devoli.com
License: AGPL 3
Platform: UNKNOWN
Classifier: Development Status :: 4 - Beta
Classifier: Programming Language :: Python
Classifier: Programming Language :: Python :: 3
Classifier: Programming Language :: Python :: 3.5
Classifier: Programming Language :: Python :: 3.6
Classifier: Programming Language :: Python :: 3.7
Classifier: Intended Audience :: Developers
Classifier: License :: OSI Approved :: GNU Affero General Public License v3
